lx_taobaoke/__init__.py
lx_taobaoke/custom_method.py
lx_taobaoke/intercept_api.py
lx_taobaoke/api/__init__.py
lx_taobaoke/api/base.py
lx_taobaoke/api/rest/AppipGetRequest.py
lx_taobaoke/api/rest/FilesGetRequest.py
lx_taobaoke/api/rest/HttpdnsGetRequest.py
lx_taobaoke/api/rest/JuItemsSearchRequest.py
lx_taobaoke/api/rest/KfcKeywordSearchRequest.py
lx_taobaoke/api/rest/OpenuidChangeRequest.py
lx_taobaoke/api/rest/OpenuidGetBymixnickRequest.py
lx_taobaoke/api/rest/OpenuidGetBytradeRequest.py
lx_taobaoke/api/rest/OpenuidGetRequest.py
lx_taobaoke/api/rest/TbkActivitylinkGetRequest.py
lx_taobaoke/api/rest/TbkContentEffectGetRequest.py
lx_taobaoke/api/rest/TbkContentGetRequest.py
lx_taobaoke/api/rest/TbkCouponGetRequest.py
lx_taobaoke/api/rest/TbkDgItemCouponGetRequest.py
lx_taobaoke/api/rest/TbkDgMaterialOptionalRequest.py
lx_taobaoke/api/rest/TbkDgNewuserOrderGetRequest.py
lx_taobaoke/api/rest/TbkDgNewuserOrderSumRequest.py
lx_taobaoke/api/rest/TbkDgOptimusMaterialRequest.py
lx_taobaoke/api/rest/TbkItemCouponGetRequest.py
lx_taobaoke/api/rest/TbkItemGetRequest.py
lx_taobaoke/api/rest/TbkItemInfoGetRequest.py
lx_taobaoke/api/rest/TbkItemRecommendGetRequest.py
lx_taobaoke/api/rest/TbkJuTqgGetRequest.py
lx_taobaoke/api/rest/TbkPrivilegeGetRequest.py
lx_taobaoke/api/rest/TbkScActivitylinkToolgetRequest.py
lx_taobaoke/api/rest/TbkScCouponBrandRecommendRequest.py
lx_taobaoke/api/rest/TbkScCouponRealtimeRecommendRequest.py
lx_taobaoke/api/rest/TbkScInvitecodeGetRequest.py
lx_taobaoke/api/rest/TbkScMaterialOptionalRequest.py
lx_taobaoke/api/rest/TbkScNewuserOrderGetRequest.py
lx_taobaoke/api/rest/TbkScNewuserOrderSumRequest.py
lx_taobaoke/api/rest/TbkScOptimusMaterialRequest.py
lx_taobaoke/api/rest/TbkScOrderDetailsGetRequest.py
lx_taobaoke/api/rest/TbkScOrderGetRequest.py
lx_taobaoke/api/rest/TbkScPublisherInfoGetRequest.py
lx_taobaoke/api/rest/TbkScPublisherInfoSaveRequest.py
lx_taobaoke/api/rest/TbkShopGetRequest.py
lx_taobaoke/api/rest/TbkShopRecommendGetRequest.py
lx_taobaoke-0.3.dist-info/METADATA
lx_taobaoke-0.3.dist-info/WHEEL
lx_taobaoke-0.3.dist-info/top_level.txt
lx_taobaoke-0.3.dist-info/RECORD
